sample.py
fast_async/__init__.py
fast_async/utils.py
fast_async/exceptions/setup_exceptions.py
fast_async/exceptions/task_exceptions.py
fast_async/types/tasks.py
fast_async-1.1.0.dist-info/LICENSE
fast_async-1.1.0.dist-info/METADATA
fast_async-1.1.0.dist-info/WHEEL
fast_async-1.1.0.dist-info/top_level.txt
fast_async-1.1.0.dist-info/RECORD
