Metadata-Version: 2.1
Name: fast-async
Version: 1.1.0
Summary: Thread based async library for python
Author-email: Bowen Feng <857514.leofeng@gmail.com>
License: The MIT License (MIT)
Keywords: async,threads
Classifier: License :: OSI Approved :: MIT License
Classifier: Programming Language :: Python
Classifier: Programming Language :: Python :: 3
Requires-Python: >=3.7
License-File: LICENSE
